{"title": "进制转换后自定义排序(100分)", "topics": ["排序算法"], "pid": "P14398", "difficulty": 3, "date": "2026年6月14日", "description_md": "# 题目内容\n\n给定一个非负整数数组 $nums$ 和一个目标进制 $base$（$2 <= base <= 16$），请完成以下操作并返回最终结果：\n1. **进制转换**：将数组中每个整数转换为 $base$ 进制的字符串（小写字母表示 $10$-$15$ 如 $10$→\"a\"，$15$→\"f\"）；\n2. **自定义排序**：对转换后的字符串数组按字符串对应的**十进制数值**降序排列；\n3. 注意：$0$ 转换为任意进制的结果均为 \"$0$\"；输入的整数均为非负整数。\n\n## 补充说明\n- $1 <= nums.length <= 100$\n- $0 <= nums[i] <= 10^6$\n- $2 <= base <= 16$\n\n\n\n\n\n\n\n## 样例1 \n\n\n\n**输入** \n\n\n\n```\n[10,25,3,15,8],16\n```\n\n\n\n**输出** \n\n\n\n```\n[\"19\",\"f\",\"a\",\"8\",\"3\"]\n```\n\n\n\n**说明**\n\n- 进制转换结果: $10→$\"$a$\"、$25→$\"$19$\"、$3→$\"$3$\"、$15→$\"$f$\"、$8→$\"$8$\";\n- 转回十进制值: \"$a$\"($10$)、\"$19$\"($25$)、\"$3$\"($3$)、\"$f$\"($15$)、\"$8$\"($8$);\n- 按数值降序: $25$(\"$19$\") $→$ $15$(\"$f$\") $→$ $10$(\"$a$\") $→$ $8$(\"$8$\") $→$ $3$(\"$3$\");\n- 无数值 / 长度相同的情况，最终结果为 $[$\"$19$\",\"$f$\",\"$a$\",\"$8$\",\"$3$\"$]$。\n\n\n## 样例2\n\n\n\n**输入** \n\n\n\n```\n[16,256,0,16],2\n```\n\n\n\n**输出** \n\n\n\n```\n[\"100000000\",\"10000\",\"10000\",\"0\"]\n```\n\n\n\n**说明**\n\n- 进制转换结果: $16→$\"$10000$\"、$256→$\"$100000000$\"、$0→$\"$0$\"、$16→$\"$10000$\";\n- 转回十进制值: 均为对应原数（$256 > 16 = 16 > 0$）;\n- 数值相同的两个 \"$10000$\"，长度和字典序均相同，顺序不限;\n- 最终结果: $[$\"$100000000$\",\"$10000$\",\"$10000$\",\"$0$\"]。", "has_signature": false, "python_signature": null, "accept_rate": "66/153", "code_templates": {"py": "# 空白解题模板\n\nclass Solution:\n    def solve(self):\n        # Write your code here\n        pass\n", "java": "// 空白解题模板\n\nclass Solution {\n    public void solve() {\n        // Write your code here\n        \n    }\n}\n", "cc": "// 空白解题模板\n\n#include <bits/stdc++.h>\nusing namespace std;\n\nclass Solution {\npublic:\n    void solve() {\n        // Write your code here\n        \n    }\n};\n", "js": "// JavaScript空白模板\n\n// Write your code here\n", "c": "// C语言空白模板\n\n#include <stdio.h>\n#include <stdlib.h>\n\n// Write your code here\n"}, "solution": "## 解题思路\n\n本题是**进制转换 + 自定义排序**，可按以下步骤处理：\n\n1. **进制转换**：对每个 $nums[i]$，若其为 $0$ 则直接得到 `\"0\"`；否则不断对 $base$ 取余得到数位，映射为 `0-9a-f` 后逆序拼接。\n2. **排序键**：转换后的字符串在 $base$ 进制下的十进制值，等于原整数 $nums[i]$ 本身，因此可直接按 $nums[i]$ **降序**排序下标。\n3. **输出**：按排序后的下标，依次输出对应的 $base$ 进制字符串。\n\n**常见假解**：\n\n- 按字符串**字典序**降序而非按数值 → 如 base $16$ 时 `\"64\"`（$100$）字典序大于 `\"ff\"`（$255$），会排错；\n- 按**升序**排列 → 与题意相反；\n- $0$ 未特判或输出空串 → 应输出 `\"0\"`；\n- 字母用大写 `A-F` → 题面要求小写；\n- 把字符串再解析成十进制比较时用了错误的 $base$。\n\n## 复杂度分析\n\n设 $n = |nums| \\le 100$，单次数值 $\\le 10^6$，进制 $\\le 16$，转换长度 $L = O(\\log_{base} nums[i]) \\le 20$。\n\n- 时间：$O(n \\cdot L + n \\log n)$，转换加排序；\n- 空间：$O(n \\cdot L)$ 存转换结果与答案。\n\n## 代码实现\n\n#code-switcher\n```python\nclass Solution:\n    def sortConvertedNums(self, nums: List[int], base: int) -> List[str]:\n        def to_base(n: int) -> str:\n            if n == 0:\n                return \"0\"\n            digits = \"0123456789abcdef\"\n            parts = []\n            while n:\n                parts.append(digits[n % base])\n                n //= base\n            return \"\".join(reversed(parts))\n\n        pairs = [(x, to_base(x)) for x in nums]\n        # 按原整数降序，等价于按 base 进制字符串的十进制值降序\n        pairs.sort(key=lambda p: p[0], reverse=True)\n        return [s for _, s in pairs]\n```\n\n```java\npublic class Solution {\n    public String[] sortConvertedNums(int[] nums, int base) {\n        int n = nums.length;\n        String[] converted = new String[n];\n        for (int i = 0; i < n; i++) {\n            converted[i] = toBase(nums[i], base);\n        }\n        int[] order = new int[n];\n        for (int i = 0; i < n; i++) order[i] = i;\n        // 选择排序下标：按原整数降序，等价于按进制串十进制值降序\n        for (int i = 0; i < n; i++) {\n            int best = i;\n            for (int j = i + 1; j < n; j++) {\n                if (nums[order[j]] > nums[order[best]]) best = j;\n            }\n            int tmp = order[i];\n            order[i] = order[best];\n            order[best] = tmp;\n        }\n        String[] ans = new String[n];\n        for (int i = 0; i < n; i++) ans[i] = converted[order[i]];\n        return ans;\n    }\n\n    private String toBase(int n, int base) {\n        if (n == 0) return \"0\";\n        String digits = \"0123456789abcdef\";\n        StringBuilder sb = new StringBuilder();\n        while (n > 0) {\n            sb.append(digits.charAt(n % base));\n            n /= base;\n        }\n        return sb.reverse().toString();\n    }\n}\n```\n\n```cpp\n#include <algorithm>\n#include <string>\n#include <vector>\n\nusing namespace std;\n\nclass Solution {\n public:\n  vector<string> sortConvertedNums(vector<int>& nums, int base) {\n    int n = (int)nums.size();\n    vector<string> converted(n);\n    for (int i = 0; i < n; i++) converted[i] = toBase(nums[i], base);\n    vector<int> order(n);\n    for (int i = 0; i < n; i++) order[i] = i;\n    // 按下标排序：nums 降序等价于进制串十进制值降序\n    sort(order.begin(), order.end(), [&](int a, int b) {\n      return nums[a] > nums[b];\n    });\n    vector<string> ans(n);\n    for (int i = 0; i < n; i++) ans[i] = converted[order[i]];\n    return ans;\n  }\n\n private:\n  string toBase(int n, int base) {\n    if (n == 0) return \"0\";\n    const string digits = \"0123456789abcdef\";\n    string s;\n    while (n > 0) {\n      s.push_back(digits[n % base]);\n      n /= base;\n    }\n    reverse(s.begin(), s.end());\n    return s;\n  }\n};\n```\n\n```javascript\nvar sortConvertedNums = function(nums, base) {\n    // 进制字符映射\n    var digits = \"0123456789abcdef\";\n    // 将数字转换为 base 进制字符串\n    function toBase(n) {\n        if (n === 0) return \"0\";\n        var parts = [];\n        while (n > 0) {\n            parts.push(digits[n % base]);\n            n = Math.floor(n / base);\n        }\n        return parts.reverse().join('');\n    }\n    // 转换每个数字\n    var converted = nums.map(function(x) { return toBase(x); });\n    // 按原整数降序排列下标\n    var order = [];\n    for (var i = 0; i < nums.length; i++) order.push(i);\n    order.sort(function(a, b) { return nums[b] - nums[a]; });\n    // 按排序后的下标收集结果\n    var result = [];\n    for (var i = 0; i < order.length; i++) {\n        result.push(converted[order[i]]);\n    }\n    return result;\n};\n```\n\n```c\nchar** sortConvertedNums(int* nums, int numsSize, int base, int* returnSize) {\n    *returnSize = numsSize;\n    // 字符映射表\n    const char* digits = \"0123456789abcdef\";\n\n    // 转换为 base 进制字符串\n    char** converted = (char**)malloc(numsSize * sizeof(char*));\n    for (int i = 0; i < numsSize; i++) {\n        int n = nums[i];\n        if (n == 0) {\n            converted[i] = (char*)malloc(2);\n            converted[i][0] = '0';\n            converted[i][1] = '\\0';\n            continue;\n        }\n        char buf[32];\n        int pos = 0;\n        while (n > 0) {\n            buf[pos++] = digits[n % base];\n            n /= base;\n        }\n        // 逆序拼回\n        converted[i] = (char*)malloc(pos + 1);\n        for (int j = 0; j < pos; j++) {\n            converted[i][j] = buf[pos - 1 - j];\n        }\n        converted[i][pos] = '\\0';\n    }\n\n    // 按原整数降序排列下标\n    int* order = (int*)malloc(numsSize * sizeof(int));\n    for (int i = 0; i < numsSize; i++) order[i] = i;\n    // 选择排序\n    for (int i = 0; i < numsSize; i++) {\n        int best = i;\n        for (int j = i + 1; j < numsSize; j++) {\n            if (nums[order[j]] > nums[order[best]]) best = j;\n        }\n        int tmp = order[i];\n        order[i] = order[best];\n        order[best] = tmp;\n    }\n\n    // 按排序后的下标收集结果\n    char** result = (char**)malloc(numsSize * sizeof(char*));\n    for (int i = 0; i < numsSize; i++) {\n        result[i] = converted[order[i]];\n    }\n    free(converted);\n    free(order);\n    return result;\n}\n```\n#code-switcher\n\n#hot100-card {\n  title: \"LeetCode Hot 100系统复习笔记\",\n  btn: \"开始复习\",\n  href: \"/codenote/hot100\",\n}\n"}